rltime/__init__.py
rltime/eval.py
rltime/train.py
rltime/acting/__init__.py
rltime/acting/acting_interface.py
rltime/acting/actor.py
rltime/acting/actor_pool.py
rltime/acting/actor_wrapper.py
rltime/acting/async_actor.py
rltime/acting/create.py
rltime/acting/ray_pool.py
rltime/configs/atari_iqn_lstm.json
rltime/configs/atari_ppo.json
rltime/configs/cartpole_a2c.json
rltime/configs/cartpole_common.json
rltime/configs/cartpole_dqn.json
rltime/configs/cartpole_iqn.json
rltime/configs/cartpole_ppo.json
rltime/configs/mountaincar_continuous_ppo.json
rltime/configs/ple_flappy_bird_iqn_lstm.json
rltime/configs/env_wrappers/atari.json
rltime/configs/env_wrappers/atari_lstm.json
rltime/configs/exploration/decay_0.01_10p.json
rltime/configs/exploration/decay_0.01_50p.json
rltime/configs/exploration/decay_0.01_5p.json
rltime/configs/exploration/per_actor_0.4_factor7.json
rltime/configs/exploration/per_actor_0.4_to_0.01_factor7_50p.json
rltime/configs/models/mlp_2x64.json
rltime/configs/models/nature_cnn_fc512.json
rltime/configs/models/nature_cnn_fc512_lstm512.json
rltime/configs/models/nature_cnn_fc512_lstm512_fc512.json
rltime/configs/models/nature_cnn_lstm512_fc512.json
rltime/configs/models/modules/fc256.json
rltime/configs/models/modules/fc512.json
rltime/configs/models/modules/fc64.json
rltime/configs/models/modules/lstm512.json
rltime/configs/models/modules/nature_cnn.json
rltime/configs/models/modules/nature_cnn_small.json
rltime/env_wrappers/__init__.py
rltime/env_wrappers/atari.py
rltime/env_wrappers/common.py
rltime/env_wrappers/vec_env/__init__.py
rltime/env_wrappers/vec_env/common.py
rltime/env_wrappers/vec_env/simple.py
rltime/env_wrappers/vec_env/sub_proc.py
rltime/exploration/__init__.py
rltime/exploration/base.py
rltime/exploration/epsilon_greedy.py
rltime/general/__init__.py
rltime/general/allowed_modules.py
rltime/general/backend.py
rltime/general/compression.py
rltime/general/config.py
rltime/general/config_template.py
rltime/general/loggers.py
rltime-0.1.2.dist-info/LICENSE
rltime-0.1.2.dist-info/METADATA
rltime-0.1.2.dist-info/WHEEL
rltime-0.1.2.dist-info/top_level.txt
rltime-0.1.2.dist-info/RECORD
